{
  "appPageId" : "25c85f12-183d-4304-a95d-293ac7dca2bf",
  "componentName" : "siteforce:sldsTwoCol84SidebarFeaturedLayout",
  "dataProviders" : [ ],
  "id" : "5393dff7-1080-450c-b81a-9e4d4966c21d",
  "label" : "Topic Detail",
  "regions" : [ {
    "components" : [ {
      "componentAttributes" : {
        "bannerText" : "",
        "bannerTextWithKnowledge" : "Explore other <a href=\"javascript:void(0)\" class=\"headlineArticles\">articles</a> and <a href=\"javascript:void(0)\" class=\"headlineDiscussions\">discussions</a> on this topic.",
        "bannerTextWithoutKnowledge" : "Explore other <a href=\"javascript:void(0)\" class=\"headlineDiscussions\">discussions</a> on this topic.",
        "pageType" : "topic",
        "showSubTopics" : true,
        "title" : "Welcome!",
        "uniqueNameOrId" : ""
      },
      "componentName" : "forceCommunity:headline",
      "id" : "ec6d1975-d5c3-4925-b816-bb1380026aba",
      "renderPriority" : "NEUTRAL",
      "renditionMap" : { },
      "type" : "component"
    } ],
    "id" : "fbe4f050-9d37-44c2-ae27-3f8968f79950",
    "regionName" : "header",
    "type" : "region"
  }, {
    "components" : [ {
      "componentAttributes" : {
        "title" : "Description",
        "topicId" : "{!recordId}"
      },
      "componentName" : "forceCommunity:topicDescription",
      "id" : "699d44d5-25ec-4431-9b38-0708e8f24aed",
      "renderPriority" : "NEUTRAL",
      "renditionMap" : { },
      "type" : "component"
    }, {
      "componentAttributes" : {
        "showArticles" : true,
        "showFollowers" : true,
        "showPosts" : true,
        "showTalkingAbout" : true,
        "topicId" : "{!recordId}"
      },
      "componentName" : "forceCommunity:topicMetrics",
      "id" : "6436f951-0cdf-4cfc-87f7-4298ec5a720f",
      "renderPriority" : "NEUTRAL",
      "renditionMap" : { },
      "type" : "component"
    }, {
      "componentAttributes" : {
        "buttonAlignment" : "center",
        "buttonBgColor" : "",
        "buttonBgHoverColor" : "",
        "buttonBorderColor" : "",
        "buttonMaxWidth" : 100,
        "buttonRadius" : 0,
        "buttonTextColor" : "",
        "buttonTextHoverColor" : "",
        "confirmationMessage" : "Got it!",
        "followUpPromptLabel" : "Can we close your question?",
        "isAskFollowPromptEnabled" : true,
        "isIncludeArticlesEnabled" : false,
        "isIncludeDiscussionsEnabled" : true,
        "isInitialSatisfactionPromptEnabled" : true,
        "isPublisherDeflectionEnabled" : true,
        "label" : "Ask a Question",
        "maxSuggestions" : 5,
        "satisfactionPromptLabel" : "Did we help to answer your question?",
        "showDetails" : false,
        "showTopics" : true,
        "uneditableTopics" : false
      },
      "componentName" : "forceCommunity:askCommunity",
      "id" : "f3e38fb2-873f-48a7-b937-f09dd842f4a7",
      "renderPriority" : "NEUTRAL",
      "renditionMap" : { },
      "type" : "component"
    }, {
      "componentAttributes" : {
        "buttonAlignment" : "center",
        "buttonBgColor" : "",
        "buttonBgHoverColor" : "",
        "buttonBorderColor" : "",
        "buttonMaxWidth" : 100,
        "buttonRadius" : 0,
        "buttonTextColor" : "",
        "buttonTextHoverColor" : "",
        "recordId" : "{!recordId}",
        "showNotificationMenu" : true
      },
      "componentName" : "forceCommunity:follow",
      "id" : "7b5ae0b5-9f6a-4f25-99b5-00db3d7e957d",
      "renderPriority" : "NEUTRAL",
      "renditionMap" : { },
      "type" : "component"
    } ],
    "id" : "2adfb3ed-a4c0-4e65-a208-0c90b8d691d8",
    "regionName" : "featured",
    "type" : "region"
  }, {
    "components" : [ {
      "componentAttributes" : {
        "activeTab" : "{!selectedTab}",
        "articleListPageSize" : 10,
        "articleTabLabel" : "Articles",
        "defaultSortOrderCompactFeed" : "Relevance",
        "defaultSortOrderFullFeed" : "Relevance",
        "discussionTabLabel" : "Discussions",
        "searchTerm" : "{!term}",
        "showArticleTab" : true,
        "showCompactFeedInDiscussion" : true,
        "topicId" : "{!recordId}"
      },
      "componentName" : "forceCommunity:resultsList",
      "id" : "df8e460b-570c-49cd-8012-51f191a8de44",
      "renderPriority" : "NEUTRAL",
      "renditionMap" : { },
      "type" : "component"
    } ],
    "id" : "bb88b86f-d155-4620-bb83-e5bc0b4e3bf5",
    "regionName" : "content",
    "type" : "region"
  }, {
    "components" : [ {
      "componentAttributes" : {
        "showTopicsMetric" : true,
        "title" : "Related Topics",
        "topicId" : "{!recordId}"
      },
      "componentName" : "forceCommunity:relatedTopics",
      "id" : "80514705-ce13-4192-a5e8-3cd624db8add",
      "renderPriority" : "NEUTRAL",
      "renditionMap" : { },
      "type" : "component"
    }, {
      "componentAttributes" : {
        "title" : "Knowledgeable People",
        "topicId" : "{!recordId}"
      },
      "componentName" : "forceCommunity:knowledgeablePeople",
      "id" : "e3c74bfa-5480-4c2b-b9b7-f521d47f7dca",
      "renderPriority" : "NEUTRAL",
      "renditionMap" : { },
      "type" : "component"
    } ],
    "id" : "e4a2aeaa-5855-4b00-8514-fe54c43651f6",
    "regionName" : "sidebar",
    "type" : "region"
  }, {
    "components" : [ {
      "componentAttributes" : {
        "askCommunityLabel" : "Ask a Question",
        "buttonBgColor" : "",
        "buttonBgHoverColor" : "",
        "buttonBorderColor" : "",
        "buttonRadius" : 0,
        "buttonTextColor" : "",
        "buttonTextHoverColor" : "",
        "buttonTwoBgColor" : "",
        "buttonTwoBgHoverColor" : "",
        "buttonTwoBorderColor" : "",
        "buttonTwoRadius" : 0,
        "buttonTwoTextColor" : "",
        "buttonTwoTextHoverColor" : "",
        "confirmationMessage" : "Got it!",
        "contactSupportLabel" : "Contact Support",
        "followUpPromptLabel" : "Can we close your question?",
        "headerLabel" : "Don't see what you're looking for?",
        "isAskFollowPromptEnabled" : true,
        "isIncludeArticlesEnabled" : false,
        "isIncludeDiscussionsEnabled" : true,
        "isInitialSatisfactionPromptEnabled" : true,
        "isPublisherDeflectionEnabled" : true,
        "maxSuggestions" : 5,
        "satisfactionPromptLabel" : "Did we help to answer your question?",
        "showDetails" : false,
        "showTopics" : true
      },
      "componentName" : "siteforce:napiliFooter",
      "id" : "5f577b0b-a84a-48ce-b118-d6870c039ebb",
      "renderPriority" : "NEUTRAL",
      "renditionMap" : { },
      "type" : "component"
    } ],
    "id" : "a42ff949-1b77-4bf5-bad5-a8e48ebbdb13",
    "regionName" : "footer",
    "type" : "region"
  }, {
    "components" : [ {
      "componentAttributes" : {
        "customHeadTags" : "",
        "description" : "{!Record.Description}",
        "title" : "{!Record._Title}"
      },
      "componentName" : "forceCommunity:seoAssistant",
      "id" : "bb352741-47cd-43d3-8692-9ed1e9a8dc2e",
      "renditionMap" : { },
      "type" : "component"
    } ],
    "id" : "8c28b647-01b3-49dc-93d6-f7ce019ba8dd",
    "regionName" : "sfdcHiddenRegion",
    "type" : "region"
  } ],
  "themeLayoutType" : "Inner",
  "type" : "view",
  "viewType" : "topic"
}